README.rst
setup.py
docs/HISTORY.txt
docs/INSTALL.txt
docs/LICENSE.GPL
docs/LICENSE.txt
jarn/__init__.py
jarn.xmpp.twisted.egg-info/PKG-INFO
jarn.xmpp.twisted.egg-info/SOURCES.txt
jarn.xmpp.twisted.egg-info/dependency_links.txt
jarn.xmpp.twisted.egg-info/entry_points.txt
jarn.xmpp.twisted.egg-info/namespace_packages.txt
jarn.xmpp.twisted.egg-info/not-zip-safe
jarn.xmpp.twisted.egg-info/requires.txt
jarn.xmpp.twisted.egg-info/top_level.txt
jarn/xmpp/__init__.py
jarn/xmpp/twisted/__init__.py
jarn/xmpp/twisted/client.py
jarn/xmpp/twisted/component.py
jarn/xmpp/twisted/configure.zcml
jarn/xmpp/twisted/httpb.py
jarn/xmpp/twisted/interfaces.py
jarn/xmpp/twisted/protocols.py
jarn/xmpp/twisted/reactor.py
jarn/xmpp/twisted/reactor.zcml
jarn/xmpp/twisted/testing.py
jarn/xmpp/twisted/tests/__init__.py
jarn/xmpp/twisted/tests/test_admin.py
jarn/xmpp/twisted/tests/test_bosh.py
jarn/xmpp/twisted/tests/test_chat.py
jarn/xmpp/twisted/tests/test_clients.py
jarn/xmpp/twisted/tests/test_component.py
jarn/xmpp/twisted/tests/test_pubsub.py