Metadata-Version: 1.0
Name: jarn.xmpp.twisted
Version: 0.1
Summary: Zope/Twisted integration for jarn.xmpp packages
Home-page: https://github.com/ggozad/jarn.xmpp.twisted
Author: Yiorgis Gozadinos
Author-email: ggozad@jarn.com
License: GPL
Keywords: plone twisted xmpp
Platform: UNKNOWN
Classifier: Development Status :: 3 - Alpha
Classifier: Framework :: Plone
Classifier: Intended Audience :: Developers
Classifier: Programming Language :: Python
